{
	"configurations" : 
	[
		{
			"directories" : 
			[
				{
					"build" : ".",
					"minimumCMakeVersion" : 
					{
						"string" : "3.18"
					},
					"projectIndex" : 0,
					"source" : "."
				}
			],
			"name" : "Debug",
			"projects" : 
			[
				{
					"directoryIndexes" : 
					[
						0
					],
					"name" : "krypto"
				}
			],
			"targets" : []
		}
	],
	"kind" : "codemodel",
	"paths" : 
	{
		"build" : "C:/Users/Magnus/Desktop/krypto/out/build/x64-Debug (default)",
		"source" : "C:/Users/Magnus/Desktop/krypto"
	},
	"version" : 
	{
		"major" : 2,
		"minor" : 1
	}
}
